server.py
fb_mcp_bratrax-1.1.2.dist-info/licenses/LICENSE
fb_mcp_bratrax-1.1.2.dist-info/METADATA
fb_mcp_bratrax-1.1.2.dist-info/WHEEL
fb_mcp_bratrax-1.1.2.dist-info/entry_points.txt
fb_mcp_bratrax-1.1.2.dist-info/top_level.txt
fb_mcp_bratrax-1.1.2.dist-info/RECORD
