Metadata-Version: 2.4
Name: fb-mcp-bratrax
Version: 1.1.2
Summary: MCP server for Facebook/Meta Ads API integration enabling programmatic access to Meta Ads data
Home-page: https://github.com/gomarble-ai/facebook-mcp
Author: GoMarble AI
Author-email: GoMarble AI <support@gomarble.ai>
License: MIT
Project-URL: Homepage, https://gomarble.ai/mcp
Project-URL: Repository, https://github.com/gomarble-ai/facebook-mcp
Project-URL: Bug Reports, https://github.com/gomarble-ai/facebook-mcp/issues
Project-URL: Documentation, https://github.com/gomarble-ai/facebook-mcp/blob/main/readme.md
Project-URL: Community, https://join.slack.com/t/ai-in-ads/shared_invite/zt-36hntbyf8-FSFixmwLb9mtEzVZhsToJQ
Keywords: facebook,ads,mcp,server,meta,marketing,api,advertising,insights,campaigns,dbt,bratrax
Classifier: Development Status :: 4 - Beta
Classifier: Intended Audience :: Developers
Classifier: Intended Audience :: System Administrators
Classifier: License :: OSI Approved :: MIT License
Classifier: Operating System :: OS Independent
Classifier: Programming Language :: Python :: 3
Classifier: Programming Language :: Python :: 3.8
Classifier: Programming Language :: Python :: 3.9
Classifier: Programming Language :: Python :: 3.10
Classifier: Programming Language :: Python :: 3.11
Classifier: Programming Language :: Python :: 3.12
Classifier: Topic :: Software Development :: Libraries :: Python Modules
Classifier: Topic :: Internet :: WWW/HTTP :: Dynamic Content
Classifier: Topic :: Office/Business :: Financial :: Investment
Classifier: Topic :: Communications
Classifier: Topic :: Scientific/Engineering :: Information Analysis
Requires-Python: >=3.8
License-File: LICENSE
Requires-Dist: mcp>=1.6.0
Requires-Dist: requests>=2.32.3
Dynamic: author
Dynamic: home-page
Dynamic: license-file
Dynamic: requires-python
